[
  {
    "id": 520,
    "portefolje_rebalansering_id": 52,
    "navn": "Vår Energi",
    "ticker": "VAR",
    "kurs": 44.67,
    "antall": 226,
    "investert": 10095.0,
    "porteføljenavn": "mcap",
    "kjopsdato": "2026-04-22"
  },
  {
    "id": 514,
    "portefolje_rebalansering_id": 52,
    "navn": "Telenor",
    "ticker": "TEL",
    "kurs": 162.7,
    "antall": 62,
    "investert": 10087.0,
    "porteføljenavn": "mcap",
    "kjopsdato": "2026-04-22"
  },
  {
    "id": 516,
    "portefolje_rebalansering_id": 52,
    "navn": "Norsk Hydro",
    "ticker": "NHY",
    "kurs": 107.3,
    "antall": 94,
    "investert": 10086.0,
    "porteføljenavn": "mcap",
    "kjopsdato": "2026-04-22"
  },
  {
    "id": 519,
    "portefolje_rebalansering_id": 52,
    "navn": "Orkla",
    "ticker": "ORK",
    "kurs": 119.3,
    "antall": 84,
    "investert": 10021.0,
    "porteføljenavn": "mcap",
    "kjopsdato": "2026-04-22"
  },
  {
    "id": 518,
    "portefolje_rebalansering_id": 52,
    "navn": "Gjensidige Forsikring",
    "ticker": "GJF",
    "kurs": 263.2,
    "antall": 38,
    "investert": 10002.0,
    "porteføljenavn": "mcap",
    "kjopsdato": "2026-04-22"
  },
  {
    "id": 515,
    "portefolje_rebalansering_id": 52,
    "navn": "Aker BP",
    "ticker": "AKRBP",
    "kurs": 343.9,
    "antall": 29,
    "investert": 9973.0,
    "porteføljenavn": "mcap",
    "kjopsdato": "2026-04-22"
  },
  {
    "id": 512,
    "portefolje_rebalansering_id": 52,
    "navn": "DNB Bank",
    "ticker": "DNB",
    "kurs": 289.5,
    "antall": 34,
    "investert": 9843.0,
    "porteføljenavn": "mcap",
    "kjopsdato": "2026-04-22"
  },
  {
    "id": 511,
    "portefolje_rebalansering_id": 52,
    "navn": "Equinor",
    "ticker": "EQNR",
    "kurs": 349.6,
    "antall": 28,
    "investert": 9789.0,
    "porteføljenavn": "mcap",
    "kjopsdato": "2026-04-22"
  },
  {
    "id": 513,
    "portefolje_rebalansering_id": 52,
    "navn": "Kongsberg Gruppen",
    "ticker": "KOG",
    "kurs": 374.2,
    "antall": 26,
    "investert": 9729.0,
    "porteføljenavn": "mcap",
    "kjopsdato": "2026-04-22"
  },
  {
    "id": 517,
    "portefolje_rebalansering_id": 52,
    "navn": "Yara International",
    "ticker": "YAR",
    "kurs": 538.4,
    "antall": 18,
    "investert": 9691.0,
    "porteføljenavn": "mcap",
    "kjopsdato": "2026-04-22"
  },
  {
    "id": 525,
    "portefolje_rebalansering_id": 53,
    "navn": "SED Energy Holdings",
    "ticker": "ENH",
    "kurs": 8.43,
    "antall": 1160,
    "investert": 9779.0,
    "porteføljenavn": "overvurdert",
    "kjopsdato": "2026-04-22"
  },
  {
    "id": 526,
    "portefolje_rebalansering_id": 53,
    "navn": "Akobo Minerals",
    "ticker": "AKOBO",
    "kurs": 1.625,
    "antall": 6018,
    "investert": 9779.0,
    "porteføljenavn": "overvurdert",
    "kjopsdato": "2026-04-22"
  },
  {
    "id": 527,
    "portefolje_rebalansering_id": 53,
    "navn": "Gulf Keystone Petroleum",
    "ticker": "GKP",
    "kurs": 23.85,
    "antall": 410,
    "investert": 9778.0,
    "porteføljenavn": "overvurdert",
    "kjopsdato": "2026-04-22"
  },
  {
    "id": 524,
    "portefolje_rebalansering_id": 53,
    "navn": "Aprila Bank",
    "ticker": "APRILA",
    "kurs": 9.95,
    "antall": 982,
    "investert": 9771.0,
    "porteføljenavn": "overvurdert",
    "kjopsdato": "2026-04-22"
  },
  {
    "id": 530,
    "portefolje_rebalansering_id": 53,
    "navn": "Paratus Energy Services",
    "ticker": "PLSV",
    "kurs": 49.5,
    "antall": 197,
    "investert": 9752.0,
    "porteføljenavn": "overvurdert",
    "kjopsdato": "2026-04-22"
  },
  {
    "id": 522,
    "portefolje_rebalansering_id": 53,
    "navn": "Capital Tankers Corp",
    "ticker": "CAPT",
    "kurs": 126.62,
    "antall": 77,
    "investert": 9750.0,
    "porteføljenavn": "overvurdert",
    "kjopsdato": "2026-04-22"
  },
  {
    "id": 529,
    "portefolje_rebalansering_id": 53,
    "navn": "Okeanis Eco Tankers",
    "ticker": "OET",
    "kurs": 462.5,
    "antall": 21,
    "investert": 9712.0,
    "porteføljenavn": "overvurdert",
    "kjopsdato": "2026-04-22"
  },
  {
    "id": 521,
    "portefolje_rebalansering_id": 53,
    "navn": "BlueNord",
    "ticker": "BNOR",
    "kurs": 539.0,
    "antall": 18,
    "investert": 9702.0,
    "porteføljenavn": "overvurdert",
    "kjopsdato": "2026-04-22"
  },
  {
    "id": 523,
    "portefolje_rebalansering_id": 53,
    "navn": "DNB Bank",
    "ticker": "DNB",
    "kurs": 289.5,
    "antall": 33,
    "investert": 9554.0,
    "porteføljenavn": "overvurdert",
    "kjopsdato": "2026-04-22"
  },
  {
    "id": 528,
    "portefolje_rebalansering_id": 53,
    "navn": "Frontline",
    "ticker": "FRO",
    "kurs": 316.4,
    "antall": 30,
    "investert": 9492.0,
    "porteføljenavn": "overvurdert",
    "kjopsdato": "2026-04-22"
  },
  {
    "id": 533,
    "portefolje_rebalansering_id": 54,
    "navn": "Hexagon Purus",
    "ticker": "HPUR",
    "kurs": 1.146,
    "antall": 8789,
    "investert": 10072.0,
    "porteføljenavn": "undervurdert",
    "kjopsdato": "2026-04-22"
  },
  {
    "id": 540,
    "portefolje_rebalansering_id": 54,
    "navn": "Norsk Titanium",
    "ticker": "NTI",
    "kurs": 0.92,
    "antall": 10948,
    "investert": 10072.0,
    "porteføljenavn": "undervurdert",
    "kjopsdato": "2026-04-22"
  },
  {
    "id": 531,
    "portefolje_rebalansering_id": 54,
    "navn": "Atlantic Sapphire",
    "ticker": "ASA",
    "kurs": 3.155,
    "antall": 3192,
    "investert": 10071.0,
    "porteføljenavn": "undervurdert",
    "kjopsdato": "2026-04-22"
  },
  {
    "id": 532,
    "portefolje_rebalansering_id": 54,
    "navn": "Norse Atlantic",
    "ticker": "NORSE",
    "kurs": 1.852,
    "antall": 5438,
    "investert": 10071.0,
    "porteføljenavn": "undervurdert",
    "kjopsdato": "2026-04-22"
  },
  {
    "id": 537,
    "portefolje_rebalansering_id": 54,
    "navn": "Axactor",
    "ticker": "ACR",
    "kurs": 6.91,
    "antall": 1457,
    "investert": 10068.0,
    "porteføljenavn": "undervurdert",
    "kjopsdato": "2026-04-22"
  },
  {
    "id": 538,
    "portefolje_rebalansering_id": 54,
    "navn": "Cavendish Hydrogen",
    "ticker": "CAVEN",
    "kurs": 7.3,
    "antall": 1379,
    "investert": 10067.0,
    "porteføljenavn": "undervurdert",
    "kjopsdato": "2026-04-22"
  },
  {
    "id": 534,
    "portefolje_rebalansering_id": 54,
    "navn": "Polaris Media",
    "ticker": "POL",
    "kurs": 60.6,
    "antall": 166,
    "investert": 10060.0,
    "porteføljenavn": "undervurdert",
    "kjopsdato": "2026-04-22"
  },
  {
    "id": 536,
    "portefolje_rebalansering_id": 54,
    "navn": "Grieg Seafood",
    "ticker": "GSF",
    "kurs": 33.96,
    "antall": 296,
    "investert": 10052.0,
    "porteføljenavn": "undervurdert",
    "kjopsdato": "2026-04-22"
  },
  {
    "id": 535,
    "portefolje_rebalansering_id": 54,
    "navn": "OKEA",
    "ticker": "OKEA",
    "kurs": 38.95,
    "antall": 258,
    "investert": 10049.0,
    "porteføljenavn": "undervurdert",
    "kjopsdato": "2026-04-22"
  },
  {
    "id": 539,
    "portefolje_rebalansering_id": 54,
    "navn": "Odfjell B",
    "ticker": "ODFB",
    "kurs": 112.2,
    "antall": 89,
    "investert": 9986.0,
    "porteføljenavn": "undervurdert",
    "kjopsdato": "2026-04-22"
  }
]